django_scrapyd-1.0.dist-info/DESCRIPTION.rst
django_scrapyd-1.0.dist-info/METADATA
django_scrapyd-1.0.dist-info/RECORD
django_scrapyd-1.0.dist-info/WHEEL
django_scrapyd-1.0.dist-info/metadata.json
django_scrapyd-1.0.dist-info/top_level.txt
scrapyd/__init__.py
scrapyd/admin.py
scrapyd/apps.py
scrapyd/models.py
scrapyd/scrapyd.py
scrapyd/urls.py
scrapyd/views.py
scrapyd/migrations/0001_initial.py
scrapyd/migrations/__init__.py
scrapyd/templates/scrapyd/log_stats.html
scrapyd/templates/scrapyd/status.html
