Metadata-Version: 2.0
Name: django-scrapyd
Version: 1.0
Summary: Django scrapyd is a Django app to manage scrapyd
Home-page: https://github.com/devopszcom/django-scrapyd
Author: Cuong Nguyen
Author-email: cuongnb14@gmail.com
License: MIT License
Platform: UNKNOWN
Classifier: Environment :: Web Environment
Classifier: Framework :: Django
Classifier: Framework :: Django :: 2.2
Classifier: Intended Audience :: Developers
Classifier: License :: OSI Approved :: MIT License
Classifier: Operating System :: OS Independent
Classifier: Programming Language :: Python
Classifier: Programming Language :: Python :: 3.5
Classifier: Programming Language :: Python :: 3.6
Classifier: Topic :: Internet :: WWW/HTTP
Classifier: Topic :: Internet :: WWW/HTTP :: Dynamic Content
Requires-Dist: requests (>=2.18.4)
